{
    "AX": {
        "error": 0.1231737429918714, 
        "fit": "average_SEM", 
        "value": 0.41509854098161064
    }, 
    "CDD": {
        "error": 0.00020731020855214045, 
        "fit": "average_SEM", 
        "value": 0.00010753298677930918
    }, 
    "H1": {
        "error": 0.1372188869831032, 
        "fit": "average_SEM", 
        "value": -0.06409048156735177
    }, 
    "H2": {
        "error": 0.25536105189330216, 
        "fit": "average_SEM", 
        "value": -0.13328710139030592
    }, 
    "L1": {
        "error": 0.14383453061085077, 
        "fit": "average_SEM", 
        "value": -0.11288022850252068
    }, 
    "L2": {
        "error": 0.15950787609820727, 
        "fit": "average_SEM", 
        "value": -0.11722210847219686
    }
}