{
    "AX": {
        "error": 0.060266268856381235, 
        "fit": "average_SEM", 
        "value": -0.024005165453248385
    }, 
    "CDD": {
        "error": 1.4192347150643281e-05, 
        "fit": "average_SEM", 
        "value": 1.295578113058582e-06
    }, 
    "H1": {
        "error": 0.1239304749636547, 
        "fit": "average_SEM", 
        "value": 0.055509769124910235
    }, 
    "H2": {
        "error": 0.1143528269269836, 
        "fit": "average_SEM", 
        "value": -0.031124087009811775
    }, 
    "L1": {
        "error": 0.17649590737925122, 
        "fit": "average_SEM", 
        "value": -0.0903131674988496
    }, 
    "L2": {
        "error": 0.1343179892328032, 
        "fit": "average_SEM", 
        "value": -0.05492010765859353
    }
}