{
    "AX": {
        "error": 0.05792928153436497, 
        "fit": "average_SEM", 
        "value": -0.016680090758018195
    }, 
    "CDD": {
        "error": 2.4374420724540924e-05, 
        "fit": "average_SEM", 
        "value": 3.8867343391757455e-06
    }, 
    "H1": {
        "error": 0.13490022702469984, 
        "fit": "average_SEM", 
        "value": -0.0023332333696695668
    }, 
    "H2": {
        "error": 0.1305676792331798, 
        "fit": "average_SEM", 
        "value": -0.025680716847030757
    }, 
    "L1": {
        "error": 0.20004231126394478, 
        "fit": "average_SEM", 
        "value": -0.09316439898684621
    }, 
    "L2": {
        "error": 0.12598077751266698, 
        "fit": "average_SEM", 
        "value": -0.07620802101203784
    }
}