{
    "Ar36": {
        "error": 0.0013242268050611932, 
        "fit": "parabolic", 
        "value": 0.010220739688816287
    }, 
    "Ar37": {
        "error": 0.1276949693010731, 
        "fit": "linear", 
        "value": -0.031201408177144414
    }, 
    "Ar38": {
        "error": 0.21229306531614578, 
        "fit": "linear", 
        "value": -0.032419078465054402
    }, 
    "Ar39": {
        "error": 0.062436669590739222, 
        "fit": "parabolic", 
        "value": 6.6139682160678586
    }, 
    "Ar40": {
        "error": 0.12996503047912497, 
        "fit": "parabolic", 
        "value": 3.9480257869526785
    }, 
    "Ar41": {
        "error": 0.12525169197693023, 
        "fit": "average_SEM", 
        "value": -0.043968263087444941
    }
}