{
    "AX": {
        "error": 0.044421021474623144, 
        "fit": "average", 
        "value": -0.15821842182623713
    }, 
    "CDD": {
        "error": 4.033805437117005e-05, 
        "fit": "average", 
        "value": 8.757225077715703e-06
    }, 
    "H1": {
        "error": 0.03708400472049383, 
        "fit": "average", 
        "value": -0.03975723163811895
    }, 
    "H2": {
        "error": 0.09186173931135869, 
        "fit": "average", 
        "value": -0.200474770043225
    }, 
    "L1": {
        "error": 0.017560346687813033, 
        "fit": "average", 
        "value": -0.02437572080433663
    }, 
    "L2": {
        "error": 0.05179058279152449, 
        "fit": "average", 
        "value": -0.009789592033978237
    }
}