{
    "AX": {
        "error": 0.04386835062468106, 
        "fit": "average", 
        "value": -0.17835615067619137
    }, 
    "CDD": {
        "error": 5.073557595584808e-05, 
        "fit": "average", 
        "value": 1.6263418001472018e-05
    }, 
    "H1": {
        "error": 0.036323887956165195, 
        "fit": "average", 
        "value": -0.041880352208832405
    }, 
    "H2": {
        "error": 0.10246958596591646, 
        "fit": "average", 
        "value": -0.17889477626189718
    }, 
    "L1": {
        "error": 0.016464107440302772, 
        "fit": "average", 
        "value": -0.03871449596605025
    }, 
    "L2": {
        "error": 0.03407410146534705, 
        "fit": "average", 
        "value": -0.0067067433666198745
    }
}