{
    "AX": {
        "error": 0.04225135980438157, 
        "fit": "average", 
        "value": -0.16626135771689207
    }, 
    "CDD": {
        "error": 3.054072586831158e-05, 
        "fit": "average", 
        "value": 3.7530964618781583e-06
    }, 
    "H1": {
        "error": 0.033932994434588644, 
        "fit": "average", 
        "value": -0.04520466388506896
    }, 
    "H2": {
        "error": 0.09320192159245176, 
        "fit": "average", 
        "value": -0.2102988614790599
    }, 
    "L1": {
        "error": 0.017096775662097358, 
        "fit": "average", 
        "value": -0.03691938023525511
    }, 
    "L2": {
        "error": 0.04127031548484507, 
        "fit": "average", 
        "value": -0.013357554442883857
    }
}