{
    "AX": {
        "error": 0.04250943643798623, 
        "fit": "average", 
        "value": -0.1484328060671016
    }, 
    "CDD": {
        "error": 3.285592248464468e-05, 
        "fit": "average", 
        "value": 7.506192923756317e-06
    }, 
    "H1": {
        "error": 0.034797966441488255, 
        "fit": "average", 
        "value": -0.04413481097422814
    }, 
    "H2": {
        "error": 0.08726060201949827, 
        "fit": "average", 
        "value": 0.02369581327379287
    }, 
    "L1": {
        "error": 0.02072201812642288, 
        "fit": "average", 
        "value": -0.03364570849373842
    }, 
    "L2": {
        "error": 0.038458443599368425, 
        "fit": "average", 
        "value": -0.01450676404941908
    }
}