{
    "Ar36": {
        "error": 0.0013444831214678651, 
        "fit": "Parabolic", 
        "value": 0.013990746269117957
    }, 
    "Ar37": {
        "error": 0.044509923571538539, 
        "fit": "linear", 
        "value": 0.050366581643274073
    }, 
    "Ar38": {
        "error": 0.018013339703388812, 
        "fit": "linear", 
        "value": 0.097794511785296093
    }, 
    "Ar39": {
        "error": 0.051072488964495746, 
        "fit": "Parabolic", 
        "value": 10.751279474457162
    }, 
    "Ar40": {
        "error": 0.049355471826503142, 
        "fit": "Parabolic", 
        "value": 17.116575080972012
    }, 
    "Ar41": {
        "error": 0.10448442595289031, 
        "fit": "linear", 
        "value": 0.084437809323441748
    }
}