{
    "Ar36": {
        "error": 0.0014513313814713779, 
        "fit": "Parabolic", 
        "value": 0.015882207827975503
    }, 
    "Ar37": {
        "error": 0.046141183630473766, 
        "fit": "linear", 
        "value": 0.11914914122329953
    }, 
    "Ar38": {
        "error": 0.019813536110876252, 
        "fit": "linear", 
        "value": 0.38166488226938217
    }, 
    "Ar39": {
        "error": 0.064438993937921296, 
        "fit": "Parabolic", 
        "value": 35.240624132027662
    }, 
    "Ar40": {
        "error": 0.064329918639627975, 
        "fit": "Parabolic", 
        "value": 47.489112213863947
    }, 
    "Ar41": {
        "error": 0.10503112308040838, 
        "fit": "linear", 
        "value": 0.050054907086486022
    }
}