{
    "AX": {
        "error": 0.04858206466790552, 
        "fit": "average", 
        "value": -0.16669611030790424
    }, 
    "CDD": {
        "error": 0.00016684861081458577, 
        "fit": "average", 
        "value": 0.00014887282607863503
    }, 
    "H1": {
        "error": 0.03502405619176333, 
        "fit": "average", 
        "value": -0.015200969411375205
    }, 
    "H2": {
        "error": 0.11652083051961647, 
        "fit": "average", 
        "value": 0.05286348280800371
    }, 
    "L1": {
        "error": 0.017248354625157582, 
        "fit": "average", 
        "value": -0.03657320781017086
    }, 
    "L2": {
        "error": 0.04387853247580324, 
        "fit": "average", 
        "value": -0.0031485085390409824
    }
}